[
    {
        "cnt": 206,
        "id": "dJgEyreFQPw",
        "thumbnails": "https://i.ytimg.com/vi/dJgEyreFQPw/hq720.jpg?sqp=-oaymwEXCNAFEJQDSFryq4qpAwkIARUAAIhCGAE=&rs=AOn4CLD8DrHJlWHZqIhid7mSyolwMToykQ",
        "duration": "4:19",
        "title": "[#미스터트롯2] 장민호가 극찬한 무결점 무대!! 오찬성의 '바보같은 사나이' #TV조선조이 (TV CHOSUN 230202 방송)",
        "published_time": "2023-02-27",
        "owner_name": "TVCHOSUN JOY",
        "view_count": "79295"
    },
    {
        "cnt": 206,
        "id": "EqmX71WUkP8",
        "thumbnails": "https://i.ytimg.com/vi/EqmX71WUkP8/hq720_2.jpg?sqp=-oaymwExCNAFEJQDSFryq4qpAyMIARUAAIhCGADwAQH4AbYIgAKAD4oCDAgAEAEYOSBRKHIwDw==&rs=AOn4CLCvMV6QwSDEnueLIKbLTGPz8CDUBQ",
        "duration": "0:58",
        "title": "안성훈 - 그대 내 친구여 (미스터트롯2 결승전 인생곡 미션_230317 방송분) [JOY #Shorts]",
        "published_time": "2023-04-02",
        "owner_name": "TVCHOSUN JOY",
        "view_count": "72885"
    },
    {
        "cnt": 206,
        "id": "_KehyQVlDas",
        "thumbnails": "https://i.ytimg.com/vi/_KehyQVlDas/hq720_2.jpg?sqp=-oaymwExCNAFEJQDSFryq4qpAyMIARUAAIhCGADwAQH4AbYIgAKAD4oCDAgAEAEYZSBDKEAwDw==&rs=AOn4CLDMhuhmFLZFd40tBUrj1SrQE_txkQ",
        "duration": "0:52",
        "title": "나상도 – 콕콕콕 (미스터트롯2 준결승전 작곡가 곡 미션 무대_230309 방송분) [JOY #Shorts]",
        "published_time": "2023-04-11",
        "owner_name": "TVCHOSUN JOY",
        "view_count": "69839"
    },
    {
        "cnt": 206,
        "id": "U1mPgHq8bFo",
        "thumbnails": "https://i.ytimg.com/vi/U1mPgHq8bFo/hq720.jpg?sqp=-oaymwEXCNAFEJQDSFryq4qpAwkIARUAAIhCGAE=&rs=AOn4CLAf5cQzn-B9UVObgRUBIR0TOgi8bA",
        "duration": "12:49",
        "title": "[#트랄랄라브라더스] 미스터트롯2 첫 콘서트 비하인드 대방출! 비장의 무대들이 넘친다는 그 현장 속으로! #TV조선조이 #TVCHOSUN (TV CHOSUN 230517 방송)",
        "published_time": "2023-06-02",
        "owner_name": "TVCHOSUN JOY",
        "view_count": "68545"
    },
    {
        "cnt": 206,
        "id": "oA94t_93soY",
        "thumbnails": "https://i.ytimg.com/vi/oA94t_93soY/hq720.jpg?sqp=-oaymwEXCNAFEJQDSFryq4qpAwkIARUAAIhCGAE=&rs=AOn4CLBwfaxyEUTekjHG02N8huAnvj2zGg",
        "duration": "5:10",
        "title": "[#미스터트롯2] 김연자 시작하자마자 하트 눌러버린 유상욱의 환상의 매직 트롯 쇼 '앗! 뜨거' #TV조선조이 #TVCHOSUNJOY (230105 방송)",
        "published_time": "2023-02-02",
        "owner_name": "TVCHOSUN JOY",
        "view_count": "59082"
    },
    {
        "cnt": 206,
        "id": "81Ok6g8-kZ0",
        "thumbnails": "https://i.ytimg.com/vi/81Ok6g8-kZ0/hq720.jpg?sqp=-oaymwEXCNAFEJQDSFryq4qpAwkIARUAAIhCGAE=&rs=AOn4CLAXHEeIBjPLZUZrZf_Epnms7_575w",
        "duration": "9:24",
        "title": "[#트랄랄라브라더스] 미스터트롯2 순수청년 박지현의 원망을 산 나상도!? 안성훈이 빼앗은 박지현의 첫 정답 #TV조선조이 (TV CHOSUN 230503 방송)",
        "published_time": "2023-05-06",
        "owner_name": "TVCHOSUN JOY",
        "view_count": "56692"
    },
    {
        "cnt": 206,
        "id": "w8HldI_nCBE",
        "thumbnails": "https://i.ytimg.com/vi/w8HldI_nCBE/hq720.jpg?sqp=-oaymwEXCNAFEJQDSFryq4qpAwkIARUAAIhCGAE=&rs=AOn4CLA56w-V9h8_eO8qZPEOVm6i5CswUQ",
        "duration": "4:45",
        "title": "[#미스터트롯2] 메들리 미션의 아쉬움을 달래줄  완곡 버전! 진욱의 '송인' #TV조선조이 #TVCHOSUNJOY (TV CHOSUN 230323 방송)",
        "published_time": "2023-04-02",
        "owner_name": "TVCHOSUN JOY",
        "view_count": "54500"
    },
    {
        "cnt": 206,
        "id": "ve8Yizn09xQ",
        "thumbnails": "https://i.ytimg.com/vi/ve8Yizn09xQ/hq720.jpg?sqp=-oaymwEXCNAFEJQDSFryq4qpAwkIARUAAIhCGAE=&rs=AOn4CLCM9XpZjb-F7fj5FeNgQO5g-_2Sog",
        "duration": "4:27",
        "title": "[#미스터트롯2] 트롯판을 침공한 아이돌 성리의 '사나이 가슴에 비가 내리네' #TV조선조이 (TV CHOSUN 230202 방송)",
        "published_time": "2023-03-02",
        "owner_name": "TVCHOSUN JOY",
        "view_count": "53921"
    },
    {
        "cnt": 206,
        "id": "bGWgtI_ZJZ0",
        "thumbnails": "https://i.ytimg.com/vi/bGWgtI_ZJZ0/hq720.jpg?sqp=-oaymwEXCNAFEJQDSFryq4qpAwkIARUAAIhCGAE=&rs=AOn4CLCFdwHgTQv5ATv6nRizIC2k6OOkSw",
        "duration": "14:11",
        "title": "[#미스터트롯2] 어제의 동료가 오늘의 적으로! 심사 난이도 최상 임찬의 '그물' VS 오찬성의 '바보같은 사나이' #TV조선조이 (TV CHOSUN 230202 방송)",
        "published_time": "2023-03-02",
        "owner_name": "TVCHOSUN JOY",
        "view_count": "52362"
    },
    {
        "cnt": 206,
        "id": "ylPv3zlLyQs",
        "thumbnails": "https://i.ytimg.com/vi/ylPv3zlLyQs/hq720.jpg?sqp=-oaymwEXCNAFEJQDSFryq4qpAwkIARUAAIhCGAE=&rs=AOn4CLD7U_ow7YINzC8DVc240iYYu2dwNA",
        "duration": "8:16",
        "title": "[#미스터트롯2] 단짠단짠 장르 진수성찬 타장르부의 새로운 맛의 일품 무대 '리듬 속에 그 춤을' #TV조선조이 #TVCHOSUNJOY (230112 방송)",
        "published_time": "2023-02-11",
        "owner_name": "TVCHOSUN JOY",
        "view_count": "51389"
    }
]