[
    {
        "cnt": 206,
        "id": "Zkd_gq765xU",
        "thumbnails": "https://i.ytimg.com/vi/Zkd_gq765xU/hq720.jpg?sqp=-oaymwEXCNAFEJQDSFryq4qpAwkIARUAAIhCGAE=&rs=AOn4CLDZ7Yg3ejsiqV33FrjjCHT-9TbsNg",
        "duration": "3:52",
        "title": "[#미스터트롯2] 마스터 예심 최단시간 올하트 신화!! 활어 트롯의 시작을 알린 박지현의 '못난 놈' #TV조선조이 #TVCHOSUNJOY (TV CHOSUN 230323 방송)",
        "published_time": "2023-04-11",
        "owner_name": "TVCHOSUN JOY",
        "view_count": "126940"
    },
    {
        "cnt": 206,
        "id": "_g8YKO59-80",
        "thumbnails": "https://i.ytimg.com/vi/_g8YKO59-80/hq720.jpg?sqp=-oaymwEXCNAFEJQDSFryq4qpAwkIARUAAIhCGAE=&rs=AOn4CLCuabnU03V9UHRMy1wxY9bPjf9Bfw",
        "duration": "26:15",
        "title": "[#미스터트롯2] 찌르면 우유가 팡!하고 터질 것 같은 트롯 밀크남 최종'5위' 최수호 한방에 몰아보기 #TV조선조이 #TVCHOSUNJOY",
        "published_time": "2023-04-02",
        "owner_name": "TVCHOSUN JOY",
        "view_count": "125842"
    },
    {
        "cnt": 206,
        "id": "wM2V2Y7YWE0",
        "thumbnails": "https://i.ytimg.com/vi/wM2V2Y7YWE0/hq720.jpg?sqp=-oaymwEXCNAFEJQDSFryq4qpAwkIARUAAIhCGAE=&rs=AOn4CLCMJcAN6PYUF7rcmjpABxwrOTT5dQ",
        "duration": "5:38",
        "title": "[#미스터트롯2] 박지현이 가족에게 꼭 하고 싶었던 말! 박지현의 인생곡 '별빛 같은 나의 사랑아' #TV조선조이 #TVCHOSUNJOY (TV CHOSUN 230406 방송)",
        "published_time": "2023-05-02",
        "owner_name": "TVCHOSUN JOY",
        "view_count": "123550"
    },
    {
        "cnt": 206,
        "id": "w6Opdb2EPSc",
        "thumbnails": "https://i.ytimg.com/vi/w6Opdb2EPSc/hq720.jpg?sqp=-oaymwEXCNAFEJQDSFryq4qpAwkIARUAAIhCGAE=&rs=AOn4CLDDX8pAYhHMMmbWsKT6IrTLWUjrdQ",
        "duration": "6:09",
        "title": "[#미스터트롯2] 아이돌은 8년차 트롯 짝사랑은 2년차, 여심 사냥꾼 선율의 심장 어택 무대 ‘짝사랑’ #TV조선조이 #TVCHOSUNJOY (TV CHOSUN 221229 방송)",
        "published_time": "2023-01-02",
        "owner_name": "TVCHOSUN JOY",
        "view_count": "121963"
    },
    {
        "cnt": 206,
        "id": "ISHkyQfvPq8",
        "thumbnails": "https://i.ytimg.com/vi/ISHkyQfvPq8/hq720.jpg?sqp=-oaymwEXCNAFEJQDSFryq4qpAwkIARUAAIhCGAE=&rs=AOn4CLBhR9mAeaGgpVJFtJ1h4RlGYCrsbw",
        "duration": "6:42",
        "title": "[#미스터트롯2] 따뜻한 봄날에 찾아온 귀염둥이 연하남들의 유혹! 대학부의 '사랑해 누나' #TV조선조이 #TVCHOSUNJOY (230323 방송)",
        "published_time": "2023-04-02",
        "owner_name": "TVCHOSUN JOY",
        "view_count": "114047"
    },
    {
        "cnt": 206,
        "id": "5fobDq8j_qM",
        "thumbnails": "https://i.ytimg.com/vi/5fobDq8j_qM/hq720.jpg?sqp=-oaymwEXCNAFEJQDSFryq4qpAwkIARUAAIhCGAE=&rs=AOn4CLDxjWQsVGknsZxcj-7ZOJ0Nknpn7g",
        "duration": "19:53",
        "title": "[#미스터트롯2] 무대마다 레전드 찍더니 여기까지 왔다! TOP10 데스매치 무대 모음 #TV조선조이 #TVCHOSUNJOY",
        "published_time": "2023-03-11",
        "owner_name": "TVCHOSUN JOY",
        "view_count": "112211"
    },
    {
        "cnt": 206,
        "id": "k6lKxCk2v-g",
        "thumbnails": "https://i.ytimg.com/vi/k6lKxCk2v-g/hq720.jpg?sqp=-oaymwEXCNAFEJQDSFryq4qpAwkIARUAAIhCGAE=&rs=AOn4CLAlWSI94w4ox11XdMarzHcZ3iELEQ",
        "duration": "25:13",
        "title": "[#미스터트롯2] 정통의 끝판왕이자 귀여움의 끝판왕까지 차지한 최종‘美’ 진해성 한방에 몰아보기 #TV조선조이 #TVCHOSUNJOY",
        "published_time": "2023-04-02",
        "owner_name": "TVCHOSUN JOY",
        "view_count": "111872"
    },
    {
        "cnt": 206,
        "id": "_sJe4WGqiMg",
        "thumbnails": "https://i.ytimg.com/vi/_sJe4WGqiMg/hq720.jpg?sqp=-oaymwEXCNAFEJQDSFryq4qpAwkIARUAAIhCGAE=&rs=AOn4CLBqZ-XxMX6F_hOqhTj4dN9xiRUhxA",
        "duration": "5:40",
        "title": "[#미스터트롯2] 제 2대 진의 영광을 함께 한 곡 안성훈의  '그대 내 친구여' #TV조선조이 (TV CHOSUN 230323 방송)",
        "published_time": "2023-04-11",
        "owner_name": "TVCHOSUN JOY",
        "view_count": "109948"
    },
    {
        "cnt": 206,
        "id": "pVfh7ajjHm4",
        "thumbnails": "https://i.ytimg.com/vi/pVfh7ajjHm4/hq720.jpg?sqp=-oaymwEXCNAFEJQDSFryq4qpAwkIARUAAIhCGAE=&rs=AOn4CLC43g5YdVY3IMmFJfeD3PhL-DKFQA",
        "duration": "8:49",
        "title": "[#미스터트롯2] 몰입도 최상! 짙게 울리는 애절한 수묵화 보이스 송민준의 오감만족 무대 '메아리' #TV조선조이 (TV CHOSUN 230309 방송)",
        "published_time": "2023-04-02",
        "owner_name": "TVCHOSUN JOY",
        "view_count": "108528"
    },
    {
        "cnt": 206,
        "id": "YNg8o-KWfpo",
        "thumbnails": "https://i.ytimg.com/vi/YNg8o-KWfpo/hq720.jpg?sqp=-oaymwEXCNAFEJQDSFryq4qpAwkIARUAAIhCGAE=&rs=AOn4CLDOF3FPbuKLB9EUd3bS090oJsxAIw",
        "duration": "5:33",
        "title": "[#미스터트롯2] 흥이여 일어나라! 김연자와 TOP7의 완벽한 컬래버레이션 '아모르파티' #TV조선조이 #TVCHOSUNJOY (TV CHOSUN 230330 방송)",
        "published_time": "2023-04-02",
        "owner_name": "TVCHOSUN JOY",
        "view_count": "104652"
    }
]